{
    "name": "Global Information",
    "numberOfRequests": {
        "total": 9,
        "ok": 8,
        "ko": 1
    },
    "minResponseTime": {
        "total": 106,
        "ok": 106,
        "ko": 199
    },
    "maxResponseTime": {
        "total": 1997,
        "ok": 1997,
        "ko": 199
    },
    "meanResponseTime": {
        "total": 474,
        "ok": 509,
        "ko": 199
    },
    "standardDeviation": {
        "total": 556,
        "ok": 581,
        "ko": 0
    },
    "percentiles1": {
        "total": 250,
        "ok": 299,
        "ko": 199
    },
    "percentiles2": {
        "total": 495,
        "ok": 504,
        "ko": 199
    },
    "percentiles3": {
        "total": 1411,
        "ok": 1484,
        "ko": 199
    },
    "percentiles4": {
        "total": 1880,
        "ok": 1894,
        "ko": 199
    },
    "group1": {
    "name": "t < 800 ms",
    "count": 7,
    "percentage": 78
},
    "group2": {
    "name": "800 ms < t < 1200 ms",
    "count": 0,
    "percentage": 0
},
    "group3": {
    "name": "t > 1200 ms",
    "count": 1,
    "percentage": 11
},
    "group4": {
    "name": "failed",
    "count": 1,
    "percentage": 11
},
    "meanNumberOfRequestsPerSecond": {
        "total": 0.9,
        "ok": 0.8,
        "ko": 0.1
    }
}